pymodaq_plugins_optosigma/__init__.py
pymodaq_plugins_optosigma/utils.py
pymodaq_plugins_optosigma/daq_move_plugins/__init__.py
pymodaq_plugins_optosigma/daq_move_plugins/daq_move_GSC.py
pymodaq_plugins_optosigma/daq_move_plugins/daq_move_RMC.py
pymodaq_plugins_optosigma/daq_move_plugins/daq_move_SBIS26.py
pymodaq_plugins_optosigma/daq_move_plugins/daq_move_SHRC203.py
pymodaq_plugins_optosigma/daq_viewer_plugins/__init__.py
pymodaq_plugins_optosigma/daq_viewer_plugins/plugins_0D/__init__.py
pymodaq_plugins_optosigma/daq_viewer_plugins/plugins_1D/__init__.py
pymodaq_plugins_optosigma/daq_viewer_plugins/plugins_2D/__init__.py
pymodaq_plugins_optosigma/daq_viewer_plugins/plugins_ND/__init__.py
pymodaq_plugins_optosigma/hardware/__init__.py
pymodaq_plugins_optosigma/hardware/gsc_VISADriver.py
pymodaq_plugins_optosigma/hardware/rmc_VISADriver.py
pymodaq_plugins_optosigma/hardware/sbis26_VISADriver.py
pymodaq_plugins_optosigma/hardware/shrc203_VISADriver.py
pymodaq_plugins_optosigma/resources/VERSION
pymodaq_plugins_optosigma/resources/__init__.py
pymodaq_plugins_optosigma/resources/config_template.toml
pymodaq_plugins_optosigma-0.4.0.dist-info/LICENSE
pymodaq_plugins_optosigma-0.4.0.dist-info/METADATA
pymodaq_plugins_optosigma-0.4.0.dist-info/WHEEL
pymodaq_plugins_optosigma-0.4.0.dist-info/entry_points.txt
pymodaq_plugins_optosigma-0.4.0.dist-info/top_level.txt
pymodaq_plugins_optosigma-0.4.0.dist-info/RECORD
