Metadata-Version: 2.1
Name: pymodaq-plugins-optosigma
Version: 0.4.0
Summary: Set of PyMoDAQ plugins for various physical measurements from optosigma
Home-page: https://github.com/NanoQM/pymodaq_plugins_optosigma
Author: Amelie Deshazer
Author-email: deshazeramelie@gmail.com
License: MIT
Classifier: Programming Language :: Python :: 3
Classifier: Development Status :: 5 - Production/Stable
Classifier: Environment :: Other Environment
Classifier: Intended Audience :: Science/Research
Classifier: Topic :: Scientific/Engineering :: Human Machine Interfaces
Classifier: Topic :: Scientific/Engineering :: Visualization
Classifier: License :: OSI Approved :: MIT License
Classifier: Operating System :: OS Independent
Classifier: Topic :: Software Development :: Libraries :: Python Modules
Classifier: Topic :: Software Development :: User Interfaces
License-File: LICENSE
Requires-Dist: toml
Requires-Dist: pymodaq>=4.3.0
Requires-Dist: pyvisa
